kafka_bridge_client/__init__.py
kafka_bridge_client/consumer.py
kafka_bridge_client/exceptions.py
kafka_bridge_client/producer.py
kafka_bridge_client-0.7.1.dist-info/LICENSE
kafka_bridge_client-0.7.1.dist-info/METADATA
kafka_bridge_client-0.7.1.dist-info/WHEEL
kafka_bridge_client-0.7.1.dist-info/RECORD
