Metadata-Version: 2.1
Name: kafka-bridge-client
Version: 0.7.1
Summary: Python client for Strimzi Kafka Bridge
Home-page: https://github.com/shafa-dev/kafka-bridge-client
License: MIT
Author: Bogdan Zaseka
Author-email: zaseka.bogdan@gmail.com
Requires-Python: >=3.6,<4.0
Classifier: License :: OSI Approved :: MIT License
Classifier: Programming Language :: Python :: 3
Classifier: Programming Language :: Python :: 3.6
Classifier: Programming Language :: Python :: 3.7
Classifier: Programming Language :: Python :: 3.8
Classifier: Programming Language :: Python :: 3.9
Classifier: Programming Language :: Python :: 3.10
Classifier: Programming Language :: Python :: 3.11
Requires-Dist: aiohttp (>=3.7.4,<4.0.0)
Requires-Dist: mypy-extensions (>=1.0.0,<2.0.0)
Requires-Dist: requests (>=2.27.1,<3.0.0)
